fastrag/__init__.py
fastrag/__main__.py
fastrag/cli.py
fastrag/events.py
fastrag/plugins.py
fastrag/settings.py
fastrag/cache/__init__.py
fastrag/cache/cache.py
fastrag/cache/entry.py
fastrag/cache/filters.py
fastrag/cache/local.py
fastrag/config/__init__.py
fastrag/config/config.py
fastrag/config/env.py
fastrag/config/settings.py
fastrag/config/loaders/__init__.py
fastrag/config/loaders/loader.py
fastrag/config/loaders/yaml.py
fastrag/embeddings/__init__.py
fastrag/embeddings/base.py
fastrag/embeddings/ollama.py
fastrag/embeddings/openai.py
fastrag/helpers/__init__.py
fastrag/helpers/experiments.py
fastrag/helpers/filters.py
fastrag/helpers/markdown_utils.py
fastrag/helpers/path_field.py
fastrag/helpers/url_field.py
fastrag/helpers/utils.py
fastrag/llms/__init__.py
fastrag/llms/llm.py
fastrag/llms/openai.py
fastrag/runner/__init__.py
fastrag/runner/arunner.py
fastrag/runner/experiment_runner.py
fastrag/runner/runner.py
fastrag/serve/__init__.py
fastrag/serve/dependencies.py
fastrag/serve/main.py
fastrag/serve/rate_limiter.py
fastrag/serve/db/__init__.py
fastrag/serve/db/database.py
fastrag/serve/db/models.py
fastrag/serve/db/repositories/sqlalchemy_repository.py
fastrag/serve/endpoints/ask.py
fastrag/serve/endpoints/chats.py
fastrag/serve/endpoints/healthz.py
fastrag/serve/endpoints/metrics.py
fastrag/serve/geolocalization/GeoLite2-Country.mmdb
fastrag/serve/geolocalization/__init__.py
fastrag/serve/geolocalization/geoip.py
fastrag/serve/monitoring/metrics.py
fastrag/steps/__init__.py
fastrag/steps/logs.py
fastrag/steps/step.py
fastrag/steps/task.py
fastrag/steps/benchmarking/__init__.py
fastrag/steps/benchmarking/chunk_quality.py
fastrag/steps/benchmarking/queryset.py
fastrag/steps/chunking/__init__.py
fastrag/steps/chunking/ollama_adapter.py
fastrag/steps/chunking/parent_child.py
fastrag/steps/chunking/recursive.py
fastrag/steps/chunking/sliding_window.py
fastrag/steps/embedding/__init__.py
fastrag/steps/embedding/openai.py
fastrag/steps/fetchers/__init__.py
fastrag_cli-0.1.8.dist-info/METADATA
fastrag_cli-0.1.8.dist-info/WHEEL
fastrag_cli-0.1.8.dist-info/entry_points.txt
fastrag_cli-0.1.8.dist-info/RECORD
